lizhankangpkg/__init__.py
lizhankangpkg/rsa.py
lizhankangpkg-1.0.5.dist-info/LICENSE
lizhankangpkg-1.0.5.dist-info/METADATA
lizhankangpkg-1.0.5.dist-info/WHEEL
lizhankangpkg-1.0.5.dist-info/top_level.txt
lizhankangpkg-1.0.5.dist-info/RECORD
