Metadata-Version: 2.1
Name: lizhankangpkg
Version: 1.0.5
Summary: 使用setuptools构建python分发包最佳实践
Classifier: Programming Language :: Python :: 3
Classifier: License :: OSI Approved :: MIT License
Classifier: Operating System :: OS Independent
License-File: LICENSE
Requires-Dist: requests
Requires-Dist: importlib-metadata
Requires-Dist: pycryptodome
Requires-Dist: pandas
Requires-Dist: openpyxl
